{"cameraMode":{"drawMode":0,"name":"Shaded","section":"Shading Mode"},"sceneLighting":false,"audioPlay":false,"sceneViewState":{"m_AlwaysRefresh":false,"showFog":true,"showSkybox":false,"showFlares":true,"showImageEffects":true,"showParticleSystems":true,"showVisualEffectGraphs":true,"m_FxEnabled":true},"in2DMode":false,"pivot":{"x":-0.00027526915073394775,"y":0.01645655743777752,"z":-0.030234381556510927},"rotation":{"x":-0.38131237030029299,"y":-0.0074819400906562809,"z":0.0031524859368801119,"w":-0.9244635701179504},"size":0.5318566560745239,"orthographic":false}